pygameBasics/__init__.py
pygamebasics-0.8.2.dist-info/METADATA
pygamebasics-0.8.2.dist-info/WHEEL
pygamebasics-0.8.2.dist-info/top_level.txt
pygamebasics-0.8.2.dist-info/RECORD
