Metadata-Version: 2.4
Name: pygameBasics
Version: 0.8.2
Summary: pygame Game Engine
Requires-Python: >=3.6
Dynamic: description
Dynamic: description-content-type
Dynamic: requires-python
Dynamic: summary
